<?xml version="1.0" encoding="utf-8" ?>
<dwsync>
<file name="perf-db2.inc.php" server="172.31.10.95" local="129176600920000000" remote="129526458600000000" />
<file name="perf-informix.inc.php" server="172.31.10.95" local="129176600920000000" remote="129526458600000000" />
<file name="perf-mssql.inc.php" server="172.31.10.95" local="129176600920000000" remote="129526458600000000" />
<file name="perf-mssqlnative.inc.php" server="172.31.10.95" local="129176600920000000" remote="129526459200000000" />
<file name="perf-mysql.inc.php" server="172.31.10.95" local="129176600920000000" remote="129526459200000000" />
<file name="perf-oci8.inc.php" server="172.31.10.95" local="129176600920000000" remote="129526459200000000" />
<file name="perf-postgres.inc.php" server="172.31.10.95" local="129176600920000000" remote="129526459200000000" />
<file name="perf-db2.inc.php" server="rrhh" local="129176600920000000" remote="129592189200000000" />
<file name="perf-informix.inc.php" server="rrhh" local="129176600920000000" remote="129592189200000000" />
<file name="perf-mssql.inc.php" server="rrhh" local="129176600920000000" remote="129592189200000000" />
<file name="perf-mssqlnative.inc.php" server="rrhh" local="129176600920000000" remote="129592189200000000" />
<file name="perf-mysql.inc.php" server="rrhh" local="129176600920000000" remote="129592189200000000" />
<file name="perf-oci8.inc.php" server="rrhh" local="129176600920000000" remote="129592189200000000" />
<file name="perf-postgres.inc.php" server="rrhh" local="129176600920000000" remote="129592189200000000" />
</dwsync>